python_ultimate_guitar-0.1.0.dist-info/DESCRIPTION.rst
python_ultimate_guitar-0.1.0.dist-info/METADATA
python_ultimate_guitar-0.1.0.dist-info/RECORD
python_ultimate_guitar-0.1.0.dist-info/WHEEL
python_ultimate_guitar-0.1.0.dist-info/metadata.json
python_ultimate_guitar-0.1.0.dist-info/top_level.txt
ultimate_guitar/__init__.py
ultimate_guitar/client.py
ultimate_guitar/command_line.py
ultimate_guitar/constants.py
ultimate_guitar/models.py
ultimate_guitar/utils.py
