Metadata-Version: 2.0
Name: python-ultimate-guitar
Version: 0.1.0
Summary: Search ultimate-guitar.com and download the results from the command line.
Home-page: https://github.com/victorfontes/python-ultimate-guitar
Author: Victor Costa
Author-email: contato@victorfontes.com
License: Copyright (c) 2017, Victor Fontes Costa
Requires-Dist: Babel (==2.5.0)
Requires-Dist: Jinja2 (==2.9.6)
Requires-Dist: MarkupSafe (==1.0)
Requires-Dist: Pygments (==2.2.0)
Requires-Dist: alabaster (==0.7.10)
Requires-Dist: beautifulsoup4 (==4.6.0)
Requires-Dist: blessings (==1.6)
Requires-Dist: bs4 (==0.0.1)
Requires-Dist: certifi (==2017.7.27.1)
Requires-Dist: chardet (==3.0.4)
Requires-Dist: click (==6.7)
Requires-Dist: curtsies (==0.2.11)
Requires-Dist: docutils (==0.14)
Requires-Dist: dotmap (==1.2.19)
Requires-Dist: greenlet (==0.4.12)
Requires-Dist: idna (==2.6)
Requires-Dist: imagesize (==0.7.1)
Requires-Dist: lxml (==3.8.0)
Requires-Dist: python-ultimate-guitar (==0.1.0)
Requires-Dist: pytz (==2017.2)
Requires-Dist: requests (==2.18.4)
Requires-Dist: rows (==0.3.1)
Requires-Dist: six (==1.10.0)
Requires-Dist: snowballstemmer (==1.2.1)
Requires-Dist: tabulate (==0.7.7)
Requires-Dist: typing (==3.6.2)
Requires-Dist: unicodecsv (==0.14.1)
Requires-Dist: urllib3 (==1.22)
Requires-Dist: wcwidth (==0.1.7)
